{"name":"Bigode Burger","address":{"street":"Avenida Rio Largo, 130 UR-2 - Ibura","city":"Recife","state":"Pernambuco","postalCode":"51340-000","full":"Avenida Rio Largo, 130 UR-2 - Ibura, Recife, Pernambuco 51340-000"},"phone":"+55 81 99599-5502","website":"https://www.tripadvisor.com.br/Restaurant_Review-g304560-d17655176-Reviews-Bigode_LanchesR-Recife_State_of_Pernambuco.html","coordinates":{"latitude":-8.113552,"longitude":-34.953953},"rating":4.8,"reviewCount":485,"priceRange":"$","cuisines":["Americana","Fast food","Internacional","Lanchonete","Restaurantes que servem cerveja"],"openingHours":{"Sunday":"18:00:00 – 00:00:00","Monday":"18:00:00 – 23:00:00","Tuesday":"18:00:00 – 23:00:00","Wednesday":"18:00:00 – 23:00:00","Thursday":"18:00:00 – 00:00:00","Friday":"18:00:00 – 00:00:00","Saturday":"18:00:00 – 00:00:00"},"features":["Aceita cartão de crédito","Acesso para cadeirantes","Entrega","Estacionamento na rua","Lugares para sentar","Mesas ao ar livre","Pagamento digital","Para levar","Permite cães","Serviço de mesa","Televisão","Wi-fi gratuito"],"description":"Hambúrguer artesanal de qualidade!","cuisinePrimary":"Americana"}