{"name":"Carlitos Burger","address":{"street":"Rua Professor Trajano de Mendonca 340 Torre","city":"Recife","state":"Pernambuco","postalCode":"50710-200","full":"Rua Professor Trajano de Mendonca 340 Torre, Recife, Pernambuco 50710-200"},"phone":"81-3228-5717","website":"https://www.tripadvisor.com.br/Restaurant_Review-g304560-d5697824-Reviews-Carlitos_Burger-Recife_State_of_Pernambuco.html","coordinates":{"latitude":-8.04387,"longitude":-34.9092},"rating":3.6,"reviewCount":43,"priceRange":"$","cuisines":["Fast food","Lanchonete"],"openingHours":{"Sunday":"18:00:00 – 01:30:00","Monday":"18:00:00 – 01:30:00","Tuesday":"18:00:00 – 02:00:00","Wednesday":"18:00:00 – 02:00:00","Thursday":"18:00:00 – 03:00:00","Friday":"18:00:00 – 05:00:00","Saturday":"18:00:00 – 05:00:00"},"features":["Acesso para cadeirantes","Entrega","Lugares para sentar","Para levar"],"description":"Acesso para cadeirantes","cuisinePrimary":"Lanchonete"}