{"name":"Emporio Vó Rita - Restaurante","address":{"street":"Rua Engenheiro Barros Lins, 372","city":"Recife","state":"Pernambuco","postalCode":null,"full":"Rua Engenheiro Barros Lins, 372, Recife, Pernambuco"},"phone":null,"website":"https://www.tripadvisor.com.br/Restaurant_Review-g304560-d27199391-Reviews-Emporio_Vo_Rita_Restaurante-Recife_State_of_Pernambuco.html","coordinates":{"latitude":-8.050485,"longitude":-34.94365},"rating":null,"reviewCount":null,"priceRange":null,"cuisines":[],"features":[],"cuisinePrimary":"Brasileira","cuisineSecond":"Sul-americana"}