{"name":"Guaiamundo Bar e Restaurante","address":{"street":"Estrada do Encanamento 1580 Ferrazopolis","city":"Recife","state":"Pernambuco","postalCode":"52070-015","full":"Estrada do Encanamento 1580 Ferrazopolis, Recife, Pernambuco 52070-015"},"phone":null,"website":"https://www.tripadvisor.com.br/Restaurant_Review-g304560-d5329067-Reviews-Guaiamundo_Bar_e_Restaurante-Recife_State_of_Pernambuco.html","coordinates":{"latitude":-8.02872,"longitude":-34.92382},"rating":3.8,"reviewCount":32,"priceRange":"$$ - $$$","cuisines":[],"features":["Acesso para cadeirantes","Lugares para sentar","Serve bebida alcoólica","Serviço de mesa"],"description":"Acesso para cadeirantes","cuisinePrimary":"Brasileira","cuisineSecond":"Bar"}