{"name":"Oxentemaki Temakeria","address":{"street":"Avenida Norte Miguel Arraes de Alencar 4121 Tamarineira","city":"Recife","state":"Pernambuco","postalCode":"52071-035","full":"Avenida Norte Miguel Arraes de Alencar 4121 Tamarineira, Recife, Pernambuco 52071-035"},"phone":null,"website":"https://www.tripadvisor.com.br/Restaurant_Review-g304560-d7398292-Reviews-Oxentemaki_Temakeria-Recife_State_of_Pernambuco.html","coordinates":{"latitude":-8.027821,"longitude":-34.90326},"rating":4.4,"reviewCount":29,"priceRange":"$","cuisines":[],"features":["Lugares para sentar","Para levar","Serviço de mesa"],"description":"Lugares para sentar","cuisinePrimary":"Japonesa"}