{"name":"Restaurante Aspen Lanches E Sorvetes","address":{"street":"Rua Flores, 129 - S 304 Santo Antônio","city":"Recife","state":"Pernambuco","postalCode":null,"full":"Rua Flores, 129 - S 304 Santo Antônio, Recife, Pernambuco"},"phone":null,"website":"https://www.tripadvisor.com.br/Restaurant_Review-g304560-d4525254-Reviews-Restaurante_Aspen_Lanches_E_Sorvetes-Recife_State_of_Pernambuco.html","coordinates":{"latitude":-8.06453,"longitude":-34.88064},"rating":5,"reviewCount":1,"priceRange":null,"cuisines":[],"features":[]}