{"name":"Sal e Brasa Grill Express Tacaruna","address":{"street":"Av. Gov. Agamenon Magalhães, 153 Shopping Tacaruna, Santo Amaro","city":"Recife","state":"Pernambuco","postalCode":"50110-900","full":"Av. Gov. Agamenon Magalhães, 153 Shopping Tacaruna, Santo Amaro, Recife, Pernambuco 50110-900"},"phone":"+(55)(81) 3412-6000","website":"https://www.tripadvisor.com.br/Restaurant_Review-g304560-d12844407-Reviews-Sal_e_Brasa_Grill_Express_Tacaruna-Recife_State_of_Pernambuco.html","coordinates":{"latitude":-8.06298,"longitude":-34.89812},"rating":3.1,"reviewCount":12,"priceRange":"$$ - $$$","cuisines":["Brasileira","Fast food","Churrasco","Sul-americana"],"openingHours":{"Sunday":"12:00:00 – 20:00:00","Monday":"09:00:00 – 22:00:00","Tuesday":"09:00:00 – 22:00:00","Wednesday":"09:00:00 – 22:00:00","Thursday":"09:00:00 – 22:00:00","Friday":"09:00:00 – 22:00:00","Saturday":"09:00:00 – 22:00:00"},"features":["Acesso para cadeirantes","Estacionamento disponível","Lugares para sentar","Serve bebida alcoólica"],"description":"Acesso para cadeirantes","cuisinePrimary":"Brasileira"}