{"name":"Terraço Carvalheira","address":{"street":"Rua  Padre Carapuceiro, 777 Shopping Recife - Cobertura Do Edifício Garagem (b4)","city":"Recife","state":"Pernambuco","postalCode":"51020-900","full":"Rua  Padre Carapuceiro, 777 Shopping Recife - Cobertura Do Edifício Garagem (b4), Recife, Pernambuco 51020-900"},"phone":"+(55)81 991971188","website":"https://www.tripadvisor.com.br/Restaurant_Review-g304560-d23122509-Reviews-Terraco_Carvalheira-Recife_State_of_Pernambuco.html","coordinates":{"latitude":-8.055802,"longitude":-34.9214},"rating":3.7,"reviewCount":63,"priceRange":"$$ - $$$","cuisines":["Brasileira","Bar","Churrasco"],"openingHours":{"Sunday":"12:00:00 – 22:00:00","Tuesday":"17:00:00 – 00:00:00","Wednesday":"17:00:00 – 00:00:00","Thursday":"17:00:00 – 00:00:00","Friday":"12:00:00 – 01:00:00","Saturday":"12:00:00 – 01:00:00"},"features":["Aceita cartão de crédito","Acesso para cadeirantes","Lugares para sentar","Reservas","Serve bebida alcoólica","Serviço de mesa"],"description":"Seja bem-vindo ao Terraço Carvalheira. Um lugar para curtir e se sentir bem. Pode vir sozinho ou em família. Encontrar amigos ou fazer novos. Comer bem, ouvir música boa, ser feliz. Seja bem-vindo à nossa casa.","cuisinePrimary":"Brasileira","cuisineSecond":"Bar"}